<lg-host browserBasedSupport="true" citrixSupport="false"
    hostname="localhost:7100" loadWeight="1" sapSupport="false"
    standalone="false" supportWANEmulation="false"
    uid="bdfe9338-4e03-43fa-8cac-b974782c1868" version="9.0.1;build=20220923-87">
    <!--****** LG NETWORK INTERFACES ******-->
    <lg-networkiface description="Software Loopback Interface 1"
        enabled="false" isLoopBack="true" name="lo">
        <!--****** LG ADDRESSES ******-->
        <lg-address enabled="false" hostname="kubernetes.docker.internal">
            <ip value="127.0.0.1"/>
        </lg-address>
        <lg-address enabled="false" hostname="0:0:0:0:0:0:0:1">
            <ip value="0:0:0:0:0:0:0:1"/>
        </lg-address>
        <!--****** END LG ADDRESSES ******-->
    </lg-networkiface>
    <lg-networkiface description="Microsoft Hyper-V Network Adapter #2"
        enabled="false" isLoopBack="false" name="eth2">
        <!--****** LG ADDRESSES ******-->
        <lg-address enabled="false" hostname="vmneolprdweu001.celesiogroup.com">
            <ip value="10.88.70.133"/>
        </lg-address>
        <lg-address enabled="false" hostname="fe80:0:0:0:60f:83a6:af60:1021%eth2">
            <ip value="fe80:0:0:0:60f:83a6:af60:1021%eth2"/>
        </lg-address>
        <!--****** END LG ADDRESSES ******-->
    </lg-networkiface>
</lg-host>
